understory/mf.py
understory/mkdn/__init__.py
understory/mkdn/hyph_en_US.dic
understory/mkdn/hyphenator.py
understory/mkdn/titlecase.py
understory/mm/__init__.py
understory/mm/__main__.py
understory/mm/parse.py
understory/mm/templating.py
understory/uri/__init__.py
understory/uri/publicsuffix.py
understory/web/README.md
understory/web/__init__.py
understory/web/__main__.py
understory/web/agent.py
understory/web/braid.py
understory/web/framework/__init__.py
understory/web/framework/letsencrypt.py
understory/web/framework/newmath.py
understory/web/framework/passphrases.json
understory/web/framework/passphrases.py
understory/web/framework/static/braid.js
understory/web/framework/static/orchid.js
understory/web/framework/static/roots.js
understory/web/framework/static/solarized.css
understory/web/framework/templates/__init__.py
understory/web/framework/templates/debug.html
understory/web/framework/templates/nginx.conf
understory/web/framework/templates/nginx_host.conf
understory/web/framework/templates/nginx_host_body.conf
understory/web/framework/templates/nginx_tor_host.conf
understory/web/framework/templates/redis.conf
understory/web/framework/templates/supervisor.conf
understory/web/framework/templates/traceback.html
understory/web/framework/util.py
understory/web/headers/__init__.py
understory/web/headers/entity.py
understory/web/headers/general.py
understory/web/headers/request.py
understory/web/headers/response.py
understory/web/headers/util.py
understory/web/response/__init__.py
understory/web/response/clienterror.py
understory/web/response/informational.py
understory/web/response/redirection.py
understory/web/response/servererror.py
understory/web/response/success.py
understory/web/response/util.py
understory_web-0.0.22.dist-info/entry_points.txt
understory_web-0.0.22.dist-info/LICENSE
understory_web-0.0.22.dist-info/WHEEL
understory_web-0.0.22.dist-info/METADATA
understory_web-0.0.22.dist-info/RECORD
