Metadata-Version: 2.1
Name: understory-web
Version: 0.0.22
Summary: Tools for metamodern web development
License: AGPL-3.0-or-later
Author: Angelo Gladding
Author-email: angelo@lahacker.net
Requires-Python: >=3.7,<4.0
Classifier: License :: OSI Approved :: GNU Affero General Public License v3 or later (AGPLv3+)
Classifier: Programming Language :: Python :: 3
Classifier: Programming Language :: Python :: 3.7
Classifier: Programming Language :: Python :: 3.8
Classifier: Programming Language :: Python :: 3.9
Requires-Dist: Pillow (>=8.2.0,<9.0.0)
Requires-Dist: PyVirtualDisplay (>=2.1,<3.0)
Requires-Dist: Unidecode (>=1.2.0,<2.0.0)
Requires-Dist: acme-tiny (>=4.1.0,<5.0.0)
Requires-Dist: cssselect (>=1.1.0,<2.0.0)
Requires-Dist: dnspython (>=2.1.0,<3.0.0)
Requires-Dist: feedparser (>=6.0.2,<7.0.0)
Requires-Dist: gevent (>=21.1.2,<22.0.0)
Requires-Dist: gunicorn (>=20.1.0,<21.0.0)
Requires-Dist: hstspreload (>=2020.12.22,<2021.0.0)
Requires-Dist: httpagentparser (>=1.9.1,<2.0.0)
Requires-Dist: jsonpatch (>=1.32,<2.0)
Requires-Dist: lxml (>=4.6.3,<5.0.0)
Requires-Dist: mf2py (>=1.1.2,<2.0.0)
Requires-Dist: mf2util (>=0.5.1,<0.6.0)
Requires-Dist: mimeparse (>=0.1.3,<0.2.0)
Requires-Dist: networkx (>=2.5.1,<3.0.0)
Requires-Dist: pendulum (>=2.1.2,<3.0.0)
Requires-Dist: pycryptodome (>=3.10.1,<4.0.0)
Requires-Dist: pyscreenshot (>=3.0,<4.0)
Requires-Dist: regex (>=2021.4.4,<2022.0.0)
Requires-Dist: requests (>=2.25.1,<3.0.0)
Requires-Dist: scrypt (>=0.8.18,<0.9.0)
Requires-Dist: selenium (>=3.141.0,<4.0.0)
Requires-Dist: understory-code (>=0.0.44,<0.0.45)
Requires-Dist: understory-db (>=0.0.8,<0.0.9)
Requires-Dist: understory-fx (>=0.0.5,<0.0.6)
Requires-Dist: understory-term (>=0.0.6,<0.0.7)
Requires-Dist: vobject (>=0.9.6,<0.10.0)
Requires-Dist: watchdog (>=2.1.2,<3.0.0)
Project-URL: Homepage, https://github.com/canopy/understory-web
